{
  "title": "Briolette Tourmaline Drop Earrings",
  "description": "Drop earrings with hammered finish circular plates and briolette cut Natural pink Tourmaline measuring approximately 5.2mm x 3.2mm. 18ct yellow gold with silicon backs. Weight: 7.1g. (Pre-owned)",
  "auctionId": "auction-1",
  "lotNumber": 266,
  "category": "tourmaline",
  "images": [
    "/images/products/98689_0.jpg"
  ],
  "estimateLow": 700,
  "estimateHigh": 1000,
  "currentBid": 560,
  "bidsCount": 4,
  "featured": false,
  "specifications": []
}