{
  "title": "1.37ct Diamond Solitaire Ring GSL J SI1",
  "description": "Diamond solitaire ring with round Natural Diamond of 1.37ct (With GSL Report graded as J SI1 # AA70727). Platinum 950. Ring size: L1/2. Band width: 3.5mm - 2.1mm. Weight: 6.3g. (New)",
  "auctionId": "auction-1",
  "lotNumber": 180,
  "category": "diamond",
  "images": [
    "/images/products/94645_0.jpg",
    "/images/products/94645_1.jpg",
    "/images/products/94645_2.jpg",
    "/images/products/94645_3.jpg"
  ],
  "estimateLow": 4300,
  "estimateHigh": 4800,
  "currentBid": 3440,
  "bidsCount": 8,
  "featured": false,
  "specifications": []
}