{
  "title": "1.23ct Amethyst & Diamond Earrings",
  "description": "Amethyst and Diamond huggie earrings with emerald cut Natural Amethyst totalling 1.23ct and round Natural Diamonds totalling 0.10ct. 14ct rose gold. Hoop diameter: 1.5cm. Weight: 2.3g. (New)",
  "auctionId": "auction-1",
  "lotNumber": 312,
  "category": "miscellaneous",
  "images": [
    "https://www.solditonline.com.au/catalogue/images/2021/90554-1.23ct-amethyst---diamond-earrings.jpg",
    "https://www.solditonline.com.au/catalogue/images/2021/90554_1-1.23ct-amethyst---diamond-earrings.jpg",
    "https://www.solditonline.com.au/catalogue/images/2021/90554_2-1.23ct-amethyst---diamond-earrings.jpg",
    "https://www.solditonline.com.au/catalogue/images/2021/90554_3-1.23ct-amethyst---diamond-earrings.jpg"
  ],
  "estimateLow": 600,
  "estimateHigh": 800,
  "currentBid": 480,
  "bidsCount": 8,
  "featured": false,
  "specifications": []
}