{
  "title": "13.05ct Topaz and Diamond Earrings",
  "description": "Topaz and Diamond leverback earrings with oval shape checkerboard natural Topazs totalling 13.05ct and round natural Diamonds totalling 0.38ct (Estimated grading: H SI). 14ct white gold. Weight: 5.6g. (New)",
  "auctionId": "auction-1",
  "lotNumber": 286,
  "category": "topaz",
  "images": [
    "https://www.solditonline.com.au/catalogue/images/2021/99240-13.05ct-topaz-and-diamond-earrings.jpg",
    "https://www.solditonline.com.au/catalogue/images/2021/99240_1-13.05ct-topaz-and-diamond-earrings.jpg",
    "https://www.solditonline.com.au/catalogue/images/2021/99240_2-13.05ct-topaz-and-diamond-earrings.jpg",
    "https://www.solditonline.com.au/catalogue/images/2021/99240_3-13.05ct-topaz-and-diamond-earrings.jpg"
  ],
  "estimateLow": 1600,
  "estimateHigh": 1800,
  "currentBid": 1280,
  "bidsCount": 3,
  "featured": false,
  "specifications": []
}