{
  "title": "0.50ct Diamond Dress Earrings",
  "description": "Clip-on earrings (with foldable posts for both pierced and non-pierced ears) with round Natural Diamonds totalling 0.50ct (Estimated grading: HIJ SI-P1). 18ct white gold. Weight: 6.8g. (Pre-owned)",
  "auctionId": "auction-1",
  "lotNumber": 325,
  "category": "diamond",
  "images": [
    "/images/products/97170_0.jpg"
  ],
  "estimateLow": 2200,
  "estimateHigh": 2400,
  "currentBid": 1760,
  "bidsCount": 2,
  "featured": false,
  "specifications": []
}