{
  "title": "Christian Dior Rose des Vents Necklace",
  "description": "Christian Dior Rose des Vents Necklace with Diamond and Turquoise inlaid. One round Natural Diamond of 0.04ct. Motif diameter: 11.8mm. 18ct yellow gold attached with Christian Dior 18ct yellow gold adjustable chain. Length: 38.5cm - 42.5cm. Weight: 3.9g. With Christian Dior Certificate dated 29/09/2018 and Christian Dior box. (Pre-owned)",
  "auctionId": "auction-1",
  "lotNumber": 235,
  "category": "miscellaneous",
  "images": [
    "/images/products/98359_0.jpg"
  ],
  "estimateLow": 1800,
  "estimateHigh": 2000,
  "currentBid": 1440,
  "bidsCount": 7,
  "featured": false,
  "specifications": [
    {
      "key": "Brand",
      "value": "Christian Dior"
    }
  ]
}