{
  "title": "1.02ct Loose Diamond Parcel",
  "description": "A loose parcel of 12 round brilliant cut Natural Diamonds totalling 1.02ct (Estimated grading: G-H VVS-VS). Approximate size: 2.85mm. (Pre-owned)",
  "auctionId": "auction-1",
  "lotNumber": 116,
  "category": "diamond",
  "images": [
    "/images/products/98884_0.jpg",
    "/images/products/98884_1.jpg",
    "/images/products/98884_2.jpg",
    "/images/products/98884_3.jpg"
  ],
  "estimateLow": 1200,
  "estimateHigh": 1400,
  "currentBid": 960,
  "bidsCount": 0,
  "featured": false,
  "specifications": []
}