{
  "/_not-found/page": "app/_not-found/page.js",
  "/page": "app/page.js",
  "/categories/[slug]/page": "app/categories/[slug]/page.js",
  "/about/page": "app/about/page.js",
  "/auctions/[id]/page": "app/auctions/[id]/page.js",
  "/past-sales/page": "app/past-sales/page.js",
  "/auctions/page": "app/auctions/page.js",
  "/contact/page": "app/contact/page.js",
  "/products/page": "app/products/page.js",
  "/selling/page": "app/selling/page.js",
  "/products/[id]/page": "app/products/[id]/page.js"
}